Frankenstein_monociclo/mem.v
/* verilator lint_off DECLFILENAME */
/* verilator lint_off WIDTHTRUNC */
 // Modulo de memoria de programa 
module dmem( input clk, mem_write,
             input  [ 3:0] byte_en,
             input  [31:0] addr,
             input  [ 8:0] vaddr,
             input  [31:0] write_data,
             output [31:0] read_data,
             output [31:0] vdata
);

  reg [31:0] RAM [0:31];
  integer i;

  initial
  begin
    RAM[0] = 32'h00000000;
    RAM[1] = 32'h00000000;
    RAM[2] = 32'h00000000;
    RAM[3] = 32'h00000000;
    RAM[4] = 32'h00000000;
    RAM[5] = 32'h00000000;
    RAM[6] = 32'h00000000;
    RAM[7] = 32'h00000000;
    RAM[8] = 32'h00000000;
    RAM[9] = 32'h00000000;
    RAM[10] = 32'h00000000;
    RAM[11] = 32'h00000000;
    RAM[12] = 32'h00000000;
    RAM[13] = 32'h00000000;
    RAM[14] = 32'h00000000;
    RAM[15] = 32'h00000000;
    RAM[16] = 32'h00000000;
    RAM[17] = 32'h00000000;
    RAM[18] = 32'h00000000;
    RAM[19] = 32'h00000000;
    RAM[20] = 32'h00000000;
    RAM[21] = 32'h00000000;
    RAM[22] = 32'h00000000;
    RAM[23] = 32'h00000000;
    RAM[24] = 32'h00000000;
    RAM[25] = 32'h00000000;
    RAM[26] = 32'h00000000;
    RAM[27] = 32'h00000000;
    RAM[28] = 32'h00000000;
    RAM[29] = 32'h00000000;
    RAM[30] = 32'h00000000;
    RAM[31] = 32'h00000000;
  end

  assign vdata = RAM[{25'b0000000000000000000000000, vaddr[8:2]}]; // word aligned
  assign read_data = RAM[addr[31:2]]; // word aligned
  
  always @(posedge clk) 
    if (mem_write) 
	 begin
        //$display("RAM[%d] = %h -> %h (%b)", addr, read_data, write_data, byte_en);
		if (byte_en[0])
		  RAM[addr[31:2]][ 7: 0] <= write_data[ 7: 0];
		if (byte_en[1])
		  RAM[addr[31:2]][15: 8] <= write_data[15: 8];
		if (byte_en[2])
		  RAM[addr[31:2]][23:16] <= write_data[23:16];
		if (byte_en[3])
		  RAM[addr[31:2]][31:24] <= write_data[31:24];
	 end
endmodule

// Modulo de memoria das instruçoes
module imem( input  [8:0]  pc,
             output [31:0] instr
);

  reg [31:0] RAM[0:9];

  initial
  begin
    RAM[0] = 32'h00000293;
    RAM[1] = 32'h12c00313;
    RAM[2] = 32'h0002c383;
    RAM[3] = 32'h00138393;
    RAM[4] = 32'h00728023;
    RAM[5] = 32'h00128293;
    RAM[6] = 32'h0062d463;
    RAM[7] = 32'hfedff06f;
    RAM[8] = 32'h00000293;
    RAM[9] = 32'hfe5ff06f;
  end

  assign instr = RAM[{25'b0000000000000000000000000, pc[8:2]}]; // word aligned
endmodule

Frankenstein_monociclo/CPU_RISCV.v
/* verilator lint_off DECLFILENAME */
// Nosso processador 
module franken_riscv( input  		     clk, reset,
                      output reg [31:0] pc,
                      input      [31:0] instruction,
                      output 		     mem_write,
			          output     [3: 0] byte_enable,
                      output     [31:0] alu_result, 
			          output     [31:0] write_data,
                      input      [31:0] read_data
);

	// Registradores
	wire [31:0] src1;
	wire [31:0] src2;
	wire [31:0] data_load;

	//JUMP
	wire is_conditional_jump;
	wire [31:0] jump_add;

	//PC
	wire [31:0] next_pc;
	
	// Atualiza nosso valor de PC
	assign next_pc =	reset 					? 32'b0:
							is_conditional_jump	? jump_add:
							pc + 32'd4;
						  
	always @(posedge clk)
     pc <= next_pc;
	
	// Recebe os valores que sao passados na instruçao
	wire [6:0] opcode;
	assign opcode = instruction[6:0];
	wire [4:0] rd_;
	assign rd_ = instruction[11:7];
	wire [2:0] funct3_;
	assign funct3_ = instruction[14:12];
	wire [4:0] rs1;
	assign rs1 = instruction[19:15];
	wire [4:0] rs2;
	assign rs2 = instruction[24:20];
	wire [6:0] funct7_;
	assign funct7_ = instruction[31:25];
	
	//Instruction Type 
	wire R_type;
	assign R_type = (opcode == 7'b0110011);
	
	wire I_type;
	assign I_type = (opcode == 7'b1100111 | opcode == 7'b0000011 | opcode == 7'b0010011); //Tambem seria uma instruçao do tipo I para 64bits => 0010011
	
	wire S_type;
	assign S_type = (opcode == 7'b0100011); //Tambem seria uma instruçao do tipo S para Double ou Float => 0100111
	
	wire B_type;
	assign B_type = (opcode == 7'b1100011);
	
	wire U_type;
	assign U_type = (opcode == 7'b0110111 | opcode == 7'b0010111);
	
	wire J_type;
	assign J_type = (opcode == 7'b1101111);
	
	// Decodificaçao das instruçoes e seus respectivos tipos 
	wire [4:0] RS1;
	assign RS1 = (R_type | I_type | S_type | B_type) 	? rs1 : 5'b0;
	
	wire [4:0] RS2;
	assign RS2 = (R_type | S_type | B_type)         	? rs2 : 5'b0;

	wire [4:0] RD;
	assign RD = (R_type | I_type | U_type | J_type) 	? rd_ : 5'b0;
	
	wire [2:0] funct3;
	assign funct3 = (R_type | I_type | S_type | B_type)? funct3_ : 3'b0;
	
	wire [6:0] funct7;
	assign funct7 = (R_type)                           ? funct7_ : 7'b0;
	
	wire [31:0] imm;
	assign imm = (I_type) ? ({{20{instruction[31]}},instruction[31:20]}):
					 (S_type) ? ({{20{instruction[31]}},instruction[31:25],instruction[11:7]}):		
					 (B_type) ? ({{19{instruction[31]}},instruction[31],instruction[7],instruction[30:25],instruction[11:8],1'b0}):
					 (U_type) ? ({instruction[31:12],12'b0}):
					 (J_type) ? ({{11{instruction[31]}}, instruction[31],instruction[19:12],instruction[20],instruction[30:21],1'b0}):
					 32'b0;
					 
	//Math
	wire is_add;
	assign is_add    	= (opcode == 7'b0110011 & funct3 == 3'b000 & funct7 == 7'b0000000);
	
	wire is_addi;
	assign is_addi   	= (opcode == 7'b0010011 & funct3 == 3'b000);
	
	wire is_sub;
	assign is_sub 	  	= (opcode == 7'b0110011 & funct3 == 3'b000 & funct7 == 7'b0100000);
	
	//Logic
	wire is_xor;
	assign is_xor	 	= (opcode == 7'b0110011 & funct3 == 3'b100 & funct7 == 7'b0000000);
	
	wire is_or;
	assign is_or	 	= (opcode == 7'b0110011 & funct3 == 3'b110 & funct7 == 7'b0000000);
	
	wire is_andi;
	assign is_andi		= (opcode == 7'b0010011 & funct3 == 3'b111);
	
	//Bit operator
	wire is_slli;
	assign is_slli   	= (opcode == 7'b0010011 & funct3 == 3'b001 & funct7 == 7'b0000000);
	
	wire is_srli;
	assign is_srli	 	= (opcode == 7'b0010011 & funct3 == 3'b101 & funct7 == 7'b0000000);
	
	//PC operator 
	wire is_auipc;
	assign is_auipc  	= (opcode == 7'b0010111);
	
	//Jump 
	wire is_jal;
	assign is_jal    	= (opcode == 7'b1101111);
	
	wire is_lui;
	assign is_lui	  	= (opcode == 7'b0110111);
	
	wire is_jalr;
	assign is_jalr   	= (opcode == 7'b1100111 & funct3 == 3'b0);
	
	wire is_bge;
	assign is_bge    	= (opcode == 7'b1100011 & funct3 == 3'b101);
	
	wire is_beq;
	assign is_beq    	= (opcode == 7'b1100011 & funct3 == 3'b0);
	
	wire is_blt;
	assign is_blt    	= (opcode == 7'b1100011 & funct3 == 3'b100);
	
	wire is_bne;
	assign is_bne    	= (opcode == 7'b1100011 & funct3 == 3'b001);
	
	//Memory 
	wire is_sw;
	assign is_sw     	= (opcode == 7'b0100011 & funct3 == 3'b010);
	
	wire is_lw;
	assign is_lw     	= (opcode == 7'b0000011 & funct3 == 3'b010);
	
	wire is_sb;
	assign is_sb		= (opcode == 7'b0100011 & funct3 == 3'b000);
	
	wire is_lbu;
	assign is_lbu		= (opcode == 7'b0000011 & funct3 == 3'b100);

	//---------------------------- Controler ---------------------------------------------//
	
	wire is_mem_reg;
	wire reg_write;
	
	//Condiçao de escrita na memoria
	assign mem_write = S_type;
	
	//Condiçao de salto
	assign is_conditional_jump = (is_beq || is_bne || is_blt || is_bge || is_jal || is_jalr);
	
	//Escrita da memoria para o registrador
	assign is_mem_reg = is_lw || is_lbu;
	
	// Condicional para escrita nos registradores
	assign reg_write = (R_type || S_type || B_type || I_type || U_type) && RD != 5'b0;
	
	
	//-------------------------------------ALU-------------------------------------------------//
	wire [31:0] result;
	assign result = 	is_add   	? src1 + src2:
							is_addi		? src1 + imm:
							is_sub		? src1 - src2:
							is_andi		? src1 & imm:
							is_or			? src1 | src2:
							is_slli		? src1 << imm[4:0]:
							is_srli		? src1 >> imm[4:0]:
							is_auipc		? pc + $signed(imm):
							J_type   	? jump_add:
							S_type 		? src1 + imm: 
							is_lw			? src1 + imm: 
							is_sw			? src1 + imm: 
							is_lui		? imm:
							is_xor		? src1 ^ src2:
							is_lbu		? src1 + imm:
							32'b0;
							
	// Recebe o resultado da alu.
	assign alu_result = result;
	
	// Caso nossa instruçao seja de JUMP, temos que calcular a nova posiçao para nosso PC.
	assign jump_add =	is_jal  													? pc 					+ $signed(imm):
							is_jalr 													? $signed(src1) 	+ $signed(imm):
							(is_beq && ($signed(src1) == $signed(src2))) ? pc		 			+ $signed(imm) :
							(is_bne && ($signed(src1) != $signed(src2))) ? pc 					+ $signed(imm):
							(is_blt && ($signed(src1)  < $signed(src2)))	? pc			 		+ $signed(imm):
							(is_bge && ($signed(src1) >= $signed(src2)))	? pc 					+ $signed(imm):
							pc + 32'd4;

	// Valor que sera salvo na nossa memoria e a condicional de escrita
	assign write_data = is_sw ? src2 : (is_sb ? (alu_result[1:0]==3 ? {src2[7:0], 24'h000000} : 
														      alu_result[1:0]==2 ? {8'h00, src2[7:0], 16'h0000} :
														      alu_result[1:0]==1 ? {16'h0000, src2[7:0], 8'h00} :
														                           {24'h000000, src2[7:0]}) :
																							32'bX);
	
	// Escrita alinhada na memoria
	assign byte_enable = is_lbu || is_sb ? (alu_result[1:0]==3 ? 4'b1000 : // sb/lb
														 alu_result[1:0]==2 ? 4'b0100 :
														 alu_result[1:0]==1 ? 4'b0010 :
														                      4'b0001): 
														                      4'b1111;  // lw/sw
	
   //Acerta a posiçao para ser salvo em memoria 
   assign data_load = is_lbu ? (alu_result[1:0]==3 ? {24'h000000, read_data[31:24]} : 
	                             alu_result[1:0]==2 ? {24'h000000, read_data[23:16]} : 
	                             alu_result[1:0]==1 ? {24'h000000, read_data[15: 8]} : 
										                       {24'h000000, read_data[ 7: 0]}):
																	  read_data;
	
	regfile regs(clk, reg_write, RS1, RS2, RD, is_mem_reg ? data_load : alu_result, src1, src2);
	
endmodule

// Modulo de registradores
module regfile(input  wire        clk, 
               input  wire        reg_write,
               input  wire [4:0]  reg_addr1, reg_addr2, addr, 
               input  wire [31:0] write_reg, 
               output wire [31:0] rd1, rd2);
					
  reg [31:0] rf[31:0];

	always @(posedge clk) 
		if (reg_write) 
			rf[addr] <= write_reg;	
		
	assign rd1 = (reg_addr1 != 5'b0) ? rf[reg_addr1] : 32'b0; 
	assign rd2 = (reg_addr2 != 5'b0) ? rf[reg_addr2] : 32'b0;
endmodule

Frankenstein_monociclo/top.v

/* verilator lint_off WIDTHEXPAND */
/* verilator lint_off WIDTHTRUNC */
// Instancia devidamente os modulos
module top #(parameter VGA_BITS = 8) (
			 input clk, reset);

	wire [31:0] instruction, read_data, read_data_vga, write_data, alu_result;
	wire        mem_write;
	wire [8:0]  pc, address, addr_vga;
	wire [3:0]  byte_enable;

	// CPU
	franken_riscv franken_riscv(clk, reset, pc, instruction, mem_write, byte_enable, alu_result, write_data, read_data);
    //riscvmulti cpu(CLOCK_50, SW, address, write_data, mem_write, read_data, byte_enable);
				
	// Memoria 
    imem imem(pc, instruction);
  	dmem dmem(!clk, mem_write, byte_enable, alu_result, addr_vga, write_data, read_data, read_data_vga);

   
	//vga video(CLOCK_50, read_data_vga, VGA_R, VGA_G, VGA_B, VGA_HS_O, VGA_VS_O, addr_vga);

	assign read_data_vga = 32'b0;
	assign addr_vga = 9'b0;
	
    //assign VGA_BLANK_N = 1'b1;
    //assign VGA_SYNC_N  = 1'b0;  
endmodule

Frankenstein_monociclo/waveform.vcd
$version Generated by VerilatedVcd $end
$timescale 1ps $end
 $scope module TOP $end
  $var wire 1 @! clk $end
  $var wire 1 A! reset $end
  $scope module top $end
   $var wire 32 G! VGA_BITS [31:0] $end
   $var wire 1 @! clk $end
   $var wire 1 A! reset $end
   $var wire 32 - instruction [31:0] $end
   $var wire 32 B! read_data [31:0] $end
   $var wire 32 H! read_data_vga [31:0] $end
   $var wire 32 . write_data [31:0] $end
   $var wire 32 / alu_result [31:0] $end
   $var wire 1 0 mem_write $end
   $var wire 9 1 pc [8:0] $end
   $var wire 9 I! address [8:0] $end
   $var wire 9 J! addr_vga [8:0] $end
   $var wire 4 2 byte_enable [3:0] $end
   $scope module dmem $end
    $var wire 1 C! clk $end
    $var wire 1 0 mem_write $end
    $var wire 4 2 byte_en [3:0] $end
    $var wire 32 / addr [31:0] $end
    $var wire 9 J! vaddr [8:0] $end
    $var wire 32 . write_data [31:0] $end
    $var wire 32 B! read_data [31:0] $end
    $var wire 32 H! vdata [31:0] $end
    $var wire 32 ~ RAM[0] [31:0] $end
    $var wire 32 !! RAM[1] [31:0] $end
    $var wire 32 "! RAM[2] [31:0] $end
    $var wire 32 #! RAM[3] [31:0] $end
    $var wire 32 $! RAM[4] [31:0] $end
    $var wire 32 %! RAM[5] [31:0] $end
    $var wire 32 &! RAM[6] [31:0] $end
    $var wire 32 '! RAM[7] [31:0] $end
    $var wire 32 (! RAM[8] [31:0] $end
    $var wire 32 )! RAM[9] [31:0] $end
    $var wire 32 *! RAM[10] [31:0] $end
    $var wire 32 +! RAM[11] [31:0] $end
    $var wire 32 ,! RAM[12] [31:0] $end
    $var wire 32 -! RAM[13] [31:0] $end
    $var wire 32 .! RAM[14] [31:0] $end
    $var wire 32 /! RAM[15] [31:0] $end
    $var wire 32 0! RAM[16] [31:0] $end
    $var wire 32 1! RAM[17] [31:0] $end
    $var wire 32 2! RAM[18] [31:0] $end
    $var wire 32 3! RAM[19] [31:0] $end
    $var wire 32 4! RAM[20] [31:0] $end
    $var wire 32 5! RAM[21] [31:0] $end
    $var wire 32 6! RAM[22] [31:0] $end
    $var wire 32 7! RAM[23] [31:0] $end
    $var wire 32 8! RAM[24] [31:0] $end
    $var wire 32 9! RAM[25] [31:0] $end
    $var wire 32 :! RAM[26] [31:0] $end
    $var wire 32 ;! RAM[27] [31:0] $end
    $var wire 32 <! RAM[28] [31:0] $end
    $var wire 32 =! RAM[29] [31:0] $end
    $var wire 32 >! RAM[30] [31:0] $end
    $var wire 32 ?! RAM[31] [31:0] $end
    $var wire 32 K! i [31:0] $end
   $upscope $end
   $scope module franken_riscv $end
    $var wire 1 @! clk $end
    $var wire 1 A! reset $end
    $var wire 32 3 pc [31:0] $end
    $var wire 32 - instruction [31:0] $end
    $var wire 1 0 mem_write $end
    $var wire 4 2 byte_enable [3:0] $end
    $var wire 32 / alu_result [31:0] $end
    $var wire 32 . write_data [31:0] $end
    $var wire 32 B! read_data [31:0] $end
    $var wire 32 4 src1 [31:0] $end
    $var wire 32 5 src2 [31:0] $end
    $var wire 32 D! data_load [31:0] $end
    $var wire 1 6 is_conditional_jump $end
    $var wire 32 7 jump_add [31:0] $end
    $var wire 32 E! next_pc [31:0] $end
    $var wire 7 8 opcode [6:0] $end
    $var wire 5 9 rd_ [4:0] $end
    $var wire 3 : funct3_ [2:0] $end
    $var wire 5 ; rs1 [4:0] $end
    $var wire 5 < rs2 [4:0] $end
    $var wire 7 = funct7_ [6:0] $end
    $var wire 1 > R_type $end
    $var wire 1 ? I_type $end
    $var wire 1 0 S_type $end
    $var wire 1 @ B_type $end
    $var wire 1 A U_type $end
    $var wire 1 B J_type $end
    $var wire 5 C RS1 [4:0] $end
    $var wire 5 D RS2 [4:0] $end
    $var wire 5 E RD [4:0] $end
    $var wire 3 F funct3 [2:0] $end
    $var wire 7 G funct7 [6:0] $end
    $var wire 32 H imm [31:0] $end
    $var wire 1 I is_add $end
    $var wire 1 J is_addi $end
    $var wire 1 K is_sub $end
    $var wire 1 L is_xor $end
    $var wire 1 M is_or $end
    $var wire 1 N is_andi $end
    $var wire 1 O is_slli $end
    $var wire 1 P is_srli $end
    $var wire 1 Q is_auipc $end
    $var wire 1 B is_jal $end
    $var wire 1 R is_lui $end
    $var wire 1 S is_jalr $end
    $var wire 1 T is_bge $end
    $var wire 1 U is_beq $end
    $var wire 1 V is_blt $end
    $var wire 1 W is_bne $end
    $var wire 1 X is_sw $end
    $var wire 1 Y is_lw $end
    $var wire 1 Z is_sb $end
    $var wire 1 [ is_lbu $end
    $var wire 1 \ is_mem_reg $end
    $var wire 1 ] reg_write $end
    $var wire 32 / result [31:0] $end
    $scope module regs $end
     $var wire 1 @! clk $end
     $var wire 1 ] reg_write $end
     $var wire 5 C reg_addr1 [4:0] $end
     $var wire 5 D reg_addr2 [4:0] $end
     $var wire 5 E addr [4:0] $end
     $var wire 32 F! write_reg [31:0] $end
     $var wire 32 4 rd1 [31:0] $end
     $var wire 32 5 rd2 [31:0] $end
     $var wire 32 ^ rf[0] [31:0] $end
     $var wire 32 _ rf[1] [31:0] $end
     $var wire 32 ` rf[2] [31:0] $end
     $var wire 32 a rf[3] [31:0] $end
     $var wire 32 b rf[4] [31:0] $end
     $var wire 32 c rf[5] [31:0] $end
     $var wire 32 d rf[6] [31:0] $end
     $var wire 32 e rf[7] [31:0] $end
     $var wire 32 f rf[8] [31:0] $end
     $var wire 32 g rf[9] [31:0] $end
     $var wire 32 h rf[10] [31:0] $end
     $var wire 32 i rf[11] [31:0] $end
     $var wire 32 j rf[12] [31:0] $end
     $var wire 32 k rf[13] [31:0] $end
     $var wire 32 l rf[14] [31:0] $end
     $var wire 32 m rf[15] [31:0] $end
     $var wire 32 n rf[16] [31:0] $end
     $var wire 32 o rf[17] [31:0] $end
     $var wire 32 p rf[18] [31:0] $end
     $var wire 32 q rf[19] [31:0] $end
     $var wire 32 r rf[20] [31:0] $end
     $var wire 32 s rf[21] [31:0] $end
     $var wire 32 t rf[22] [31:0] $end
     $var wire 32 u rf[23] [31:0] $end
     $var wire 32 v rf[24] [31:0] $end
     $var wire 32 w rf[25] [31:0] $end
     $var wire 32 x rf[26] [31:0] $end
     $var wire 32 y rf[27] [31:0] $end
     $var wire 32 z rf[28] [31:0] $end
     $var wire 32 { rf[29] [31:0] $end
     $var wire 32 | rf[30] [31:0] $end
     $var wire 32 } rf[31] [31:0] $end
    $upscope $end
   $upscope $end
   $scope module imem $end
    $var wire 9 1 pc [8:0] $end
    $var wire 32 - instr [31:0] $end
    $var wire 32 # RAM[0] [31:0] $end
    $var wire 32 $ RAM[1] [31:0] $end
    $var wire 32 % RAM[2] [31:0] $end
    $var wire 32 & RAM[3] [31:0] $end
    $var wire 32 ' RAM[4] [31:0] $end
    $var wire 32 ( RAM[5] [31:0] $end
    $var wire 32 ) RAM[6] [31:0] $end
    $var wire 32 * RAM[7] [31:0] $end
    $var wire 32 + RAM[8] [31:0] $end
    $var wire 32 , RAM[9] [31:0] $end
   $upscope $end
  $upscope $end
 $upscope $end
$enddefinitions $end


#1
b00000000000000000000001010010011 #
b00010010110000000000001100010011 $
b00000000000000101100001110000011 %
b00000000000100111000001110010011 &
b00000000011100101000000000100011 '
b00000000000100101000001010010011 (
b00000000011000101101010001100011 )
b11111110110111111111000001101111 *
b00000000000000000000001010010011 +
b11111110010111111111000001101111 ,
b00010010110000000000001100010011 -
b00000000000000000000000000000000 .
b00000000000000000000000100101100 /
00
b000000100 1
b1111 2
b00000000000000000000000000000100 3
b00000000000000000000000000000000 4
b00000000000000000000000000000000 5
06
b00000000000000000000000000001000 7
b0010011 8
b00110 9
b000 :
b00000 ;
b01100 <
b0001001 =
0>
1?
0@
0A
0B
b00000 C
b00000 D
b00110 E
b000 F
b0000000 G
b00000000000000000000000100101100 H
0I
1J
0K
0L
0M
0N
0O
0P
0Q
0R
0S
0T
0U
0V
0W
0X
0Y
0Z
0[
0\
1]
b00000000000000000000000000000000 ^
b00000000000000000000000000000000 _
b00000000000000000000000000000000 `
b00000000000000000000000000000000 a
b00000000000000000000000000000000 b
b00000000000000000000000000000000 c
b00000000000000000000000000000000 d
b00000000000000000000000000000000 e
b00000000000000000000000000000000 f
b00000000000000000000000000000000 g
b00000000000000000000000000000000 h
b00000000000000000000000000000000 i
b00000000000000000000000000000000 j
b00000000000000000000000000000000 k
b00000000000000000000000000000000 l
b00000000000000000000000000000000 m
b00000000000000000000000000000000 n
b00000000000000000000000000000000 o
b00000000000000000000000000000000 p
b00000000000000000000000000000000 q
b00000000000000000000000000000000 r
b00000000000000000000000000000000 s
b00000000000000000000000000000000 t
b00000000000000000000000000000000 u
b00000000000000000000000000000000 v
b00000000000000000000000000000000 w
b00000000000000000000000000000000 x
b00000000000000000000000000000000 y
b00000000000000000000000000000000 z
b00000000000000000000000000000000 {
b00000000000000000000000000000000 |
b00000000000000000000000000000000 }
b00000000000000000000000000000000 ~
b00000000000000000000000000000000 !!
b00000000000000000000000000000000 "!
b00000000000000000000000000000000 #!
b00000000000000000000000000000000 $!
b00000000000000000000000000000000 %!
b00000000000000000000000000000000 &!
b00000000000000000000000000000000 '!
b00000000000000000000000000000000 (!
b00000000000000000000000000000000 )!
b00000000000000000000000000000000 *!
b00000000000000000000000000000000 +!
b00000000000000000000000000000000 ,!
b00000000000000000000000000000000 -!
b00000000000000000000000000000000 .!
b00000000000000000000000000000000 /!
b00000000000000000000000000000000 0!
b00000000000000000000000000000000 1!
b00000000000000000000000000000000 2!
b00000000000000000000000000000000 3!
b00000000000000000000000000000000 4!
b00000000000000000000000000000000 5!
b00000000000000000000000000000000 6!
b00000000000000000000000000000000 7!
b00000000000000000000000000000000 8!
b00000000000000000000000000000000 9!
b00000000000000000000000000000000 :!
b00000000000000000000000000000000 ;!
b00000000000000000000000000000000 <!
b00000000000000000000000000000000 =!
b00000000000000000000000000000000 >!
b00000000000000000000000000000000 ?!
1@!
0A!
b00000000000000000000000000000000 B!
0C!
b00000000000000000000000000000000 D!
b00000000000000000000000000001000 E!
b00000000000000000000000100101100 F!
b00000000000000000000000000001000 G!
b00000000000000000000000000000000 H!
b000000000 I!
b000000000 J!
b00000000000000000000000000000000 K!
#2
0@!
1C!
#3
b00000000000000101100001110000011 -
b00000000000000000000000000000000 /
b000001000 1
b0001 2
b00000000000000000000000000001000 3
b00000000000000000000000000001100 7
b0000011 8
b00111 9
b100 :
b00101 ;
b00000 <
b0000000 =
b00101 C
b00111 E
b100 F
b00000000000000000000000000000000 H
0J
1[
1\
b00000000000000000000000100101100 d
1@!
0C!
b00000000000000000000000000001100 E!
b00000000000000000000000000000000 F!
#4
0@!
1C!
#5
b00000000000100111000001110010011 -
b00000000000000000000000000000001 /
b000001100 1
b1111 2
b00000000000000000000000000001100 3
b00000000000000000000000000010000 7
b0010011 8
b000 :
b00111 ;
b00001 <
b00111 C
b000 F
b00000000000000000000000000000001 H
1J
0[
0\
1@!
0C!
b00000000000000000000000000010000 E!
b00000000000000000000000000000001 F!
#6
0@!
1C!
#7
b00000000011100101000000000100011 -
b00000000000000000000000000000001 .
b00000000000000000000000000000000 /
10
b000010000 1
b0001 2
b00000000000000000000000000010000 3
b00000000000000000000000000000001 5
b00000000000000000000000000010100 7
b0100011 8
b00000 9
b00101 ;
b00111 <
0?
b00101 C
b00111 D
b00000 E
b00000000000000000000000000000000 H
0J
1Z
0]
b00000000000000000000000000000001 e
1@!
0C!
b00000000000000000000000000010100 E!
b00000000000000000000000000000000 F!
#8
b00000000000000000000000000000001 ~
0@!
b00000000000000000000000000000001 B!
1C!
b00000000000000000000000000000001 D!
#9
b00000000000100101000001010010011 -
b00000000000000000000000000000000 .
b00000000000000000000000000000001 /
00
b000010100 1
b1111 2
b00000000000000000000000000010100 3
b00000000000000000000000000000000 5
b00000000000000000000000000011000 7
b0010011 8
b00101 9
b00001 <
1?
b00000 D
b00101 E
b00000000000000000000000000000001 H
1J
0Z
1]
1@!
0C!
b00000000000000000000000000011000 E!
b00000000000000000000000000000001 F!
#10
0@!
1C!
#11
b00000000011000101101010001100011 -
b00000000000000000000000000000000 /
b000011000 1
b00000000000000000000000000011000 3
b00000000000000000000000000000001 4
b00000000000000000000000100101100 5
16
b00000000000000000000000000011100 7
b1100011 8
b01000 9
b101 :
b00110 <
0?
1@
b00110 D
b00000 E
b101 F
b00000000000000000000000000001000 H
0J
1T
0]
b00000000000000000000000000000001 c
1@!
0C!
b00000000000000000000000000011100 E!
b00000000000000000000000000000000 F!
#12
0@!
1C!
#13
b11111110110111111111000001101111 -
b00000000000000000000000000001000 /
b000011100 1
b00000000000000000000000000011100 3
b00000000000000000000000000000000 4
b00000000000000000000000000000000 5
b00000000000000000000000000001000 7
b1101111 8
b00000 9
b111 :
b11111 ;
b01101 <
b1111111 =
0@
1B
b00000 C
b00000 D
b000 F
b11111111111111111111111111101100 H
0T
1@!
b00000000000000000000000000000000 B!
0C!
b00000000000000000000000000000000 D!
b00000000000000000000000000001000 E!
b00000000000000000000000000001000 F!
#14
0@!
1C!
#15
b00000000000000101100001110000011 -
b00000000000000000000000000000001 /
b000001000 1
b0010 2
b00000000000000000000000000001000 3
b00000000000000000000000000000001 4
06
b00000000000000000000000000001100 7
b0000011 8
b00111 9
b100 :
b00101 ;
b00000 <
b0000000 =
1?
0B
b00101 C
b00111 E
b100 F
b00000000000000000000000000000000 H
1[
1\
1]
1@!
b00000000000000000000000000000001 B!
0C!
b00000000000000000000000000001100 E!
b00000000000000000000000000000000 F!
#16
0@!
1C!
#17
b00000000000100111000001110010011 -
b000001100 1
b1111 2
b00000000000000000000000000001100 3
b00000000000000000000000000000000 4
b00000000000000000000000000010000 7
b0010011 8
b000 :
b00111 ;
b00001 <
b00111 C
b000 F
b00000000000000000000000000000001 H
1J
0[
0\
b00000000000000000000000000000000 e
1@!
0C!
b00000000000000000000000000000001 D!
b00000000000000000000000000010000 E!
b00000000000000000000000000000001 F!
#18
0@!
1C!
#19
b00000000011100101000000000100011 -
b00000000000000000000000100000000 .
10
b000010000 1
b0010 2
b00000000000000000000000000010000 3
b00000000000000000000000000000001 4
b00000000000000000000000000000001 5
b00000000000000000000000000010100 7
b0100011 8
b00000 9
b00101 ;
b00111 <
0?
b00101 C
b00111 D
b00000 E
b00000000000000000000000000000000 H
0J
1Z
0]
b00000000000000000000000000000001 e
1@!
0C!
b00000000000000000000000000010100 E!
